http2client/__init__.py
http2client/http2client.py
http2client-0.1.0.dist-info/LICENSE
http2client-0.1.0.dist-info/METADATA
http2client-0.1.0.dist-info/WHEEL
http2client-0.1.0.dist-info/top_level.txt
http2client-0.1.0.dist-info/RECORD
