Metadata-Version: 2.1
Name: http2client
Version: 0.1.0
Summary: A simple HTTP/2 client for Cyber Security
Home-page: https://github.com/cyal1/http2client
Author: cyal1
Author-email: dsq6115119@gmail.com
License: UNKNOWN
Platform: UNKNOWN
Classifier: Topic :: Software Development :: Libraries :: Python Modules
Classifier: Programming Language :: Python :: Implementation :: CPython
Requires-Python: >=3.8
License-File: LICENSE
Requires-Dist: h2 (>=2.6.2)
Requires-Dist: urllib3 (>=1.26.12)
Requires-Dist: setuptools
